{
  "platform": "eastmoney",
  "fetch_time": "2026-07-01 07:09:48",
  "count": 3,
  "news": [
    {
      "title": "巨额回购股揭秘 最高股息率接近11%",
      "link": "https://finance.eastmoney.com/a/202607013789942038.html",
      "source": "东方财富网",
      "detail": "价值股 黄金 坑出现了？ 今年上半年，A股市场结构性行情凸显，科技股表现亮眼， 电子 、 通信 等板块年内涨幅均超70%。以大消费、大金融为主的 价值股 则表现较弱， 食品饮料 、 非银金融 、 银行 等板块年内均跌超10%。 在此背景下， 价值股 纷纷开启回购潮。数据显示，年内落地实施的回购总额突破661亿元；另有一批回购在路上，拟回购金额上限合计逾880亿元。 巨额回购股揭秘 据证券时报·数据宝统计，截至7月1日，A股市场年内共有超700家上市公司实施回购，合计回购金额达到661.75亿元，处于历史同期高位。 其中， 美的集团 、 京东方A 、 顺丰控股 等9家公司年内回购金额均在10亿元以上；此外，还有逾百股回购金额超过亿元。 从参与主体结构来看，现金流充裕、长期盈利稳健的 行业龙头 企业构成了当前股票回购的主力军。",
      "publish_time": "2026-07-01 07:07:28"
    },
    {
      "title": "67家A股公司公告提示风险",
      "link": "https://finance.eastmoney.com/a/202606303788690066.html",
      "source": "东方财富网",
      "detail": "【导读】67家A股公司公告提示风险，回应 玻璃基板 、AI、存储等热点 6月30日晚间，67家A股公司发布股票交易异常波动公告或股票交易风险提示公告，分别是 寒武纪 、 屹唐股份 、 德龙激光 、 晶升股份 、 东芯股份 、 芯源微 、 艾森股份 、 明微电子 、 福光股份 、 深科达 、 中科飞测 、 思林杰 、 富信科技 、 天准科技 、天承科技、 中科蓝讯 、盛科 通信 、 长光华芯 、 昀冢科技 、 敏芯股份 、 恒烁股份 、 源杰科技 、 颀中科技 、 华特气体 、 埃科光电 、 茂莱光学 、 方邦股份 、 有研新材 、 红星发展 、 绿的谐波 、 兴业股份 、 宝武镁业 、 技源集团 、 ST合力泰 、 声迅股份 、 魅视科技 、 成都路桥 、 贵广网络 、 聚和材料 、 银河微电 、 金海通 、 卓郎智能 、 新洁能 、 华恒生物 、 天普股份 、 深科技 、 凯盛科技 、 ",
      "publish_time": "2026-07-01 07:07:31"
    },
    {
      "title": "67家A股公司公告提示风险 回应玻璃基板、AI、存储等热点",
      "link": "https://finance.eastmoney.com/a/202606303788690066.html",
      "source": "东方财富网",
      "detail": "【导读】67家A股公司公告提示风险，回应 玻璃基板 、AI、存储等热点 6月30日晚间，67家A股公司发布股票交易异常波动公告或股票交易风险提示公告，分别是 寒武纪 、 屹唐股份 、 德龙激光 、 晶升股份 、 东芯股份 、 芯源微 、 艾森股份 、 明微电子 、 福光股份 、 深科达 、 中科飞测 、 思林杰 、 富信科技 、 天准科技 、天承科技、 中科蓝讯 、盛科 通信 、 长光华芯 、 昀冢科技 、 敏芯股份 、 恒烁股份 、 源杰科技 、 颀中科技 、 华特气体 、 埃科光电 、 茂莱光学 、 方邦股份 、 有研新材 、 红星发展 、 绿的谐波 、 兴业股份 、 宝武镁业 、 技源集团 、 ST合力泰 、 声迅股份 、 魅视科技 、 成都路桥 、 贵广网络 、 聚和材料 、 银河微电 、 金海通 、 卓郎智能 、 新洁能 、 华恒生物 、 天普股份 、 深科技 、 凯盛科技 、 ",
      "publish_time": "2026-07-01 07:07:54"
    }
  ]
}